{"cameraMode":{"drawMode":0,"name":"Shaded","section":"Shading Mode"},"sceneLighting":true,"audioPlay":false,"sceneViewState":{"m_AlwaysRefresh":false,"showFog":true,"showSkybox":true,"showFlares":true,"showImageEffects":true,"showParticleSystems":true,"showVisualEffectGraphs":true,"m_FxEnabled":true},"in2DMode":false,"pivot":{"x":17.571821212768556,"y":2.3668785095214845,"z":8.982606887817383},"rotation":{"x":-0.32459771633148196,"y":-0.3311907947063446,"z":0.1225137785077095,"w":-0.8774808049201965},"size":24.506044387817384,"orthographic":false}